cgo_sfdc_pub_sub/ChangeEventHeaderUtility.py
cgo_sfdc_pub_sub/PubSub.py
cgo_sfdc_pub_sub/__init__.py
cgo_sfdc_pub_sub/pubsub_api_pb2.py
cgo_sfdc_pub_sub/pubsub_api_pb2_grpc.py
cgo_sfdc_pub_sub-1.0.1.dist-info/LICENSE
cgo_sfdc_pub_sub-1.0.1.dist-info/METADATA
cgo_sfdc_pub_sub-1.0.1.dist-info/WHEEL
cgo_sfdc_pub_sub-1.0.1.dist-info/top_level.txt
cgo_sfdc_pub_sub-1.0.1.dist-info/RECORD
